[
    {
        "question": "Which of the following is a key area where Artificial Intelligence (AI) is having a significant impact in the healthcare industry?",
        "options": {
            "A": "Pharmaceutical research",
            "B": "Television production",
            "C": "Improving diagnostics, patient care, and medical research",
            "D": "Textile manufacturing"
        },
        "answer": "C"
    },
    {
        "question": "What is the primary focus of ongoing research in AI for healthcare?",
        "options": {
            "A": "Decreasing accuracy",
            "B": "Ensuring fairness",
            "C": "Making healthcare less accessible worldwide",
            "D": "Improving efficiency in non-healthcare sectors"
        },
        "answer": "B"
    },
    {
        "question": "What is a primary advantage of AI-powered medical systems?",
        "options": {
            "A": "They can provide emotional support to patients",
            "B": "They have unlimited work hours",
            "C": "They can analyze vast amounts of medical data and detect patterns that might be overlooked by human doctors",
            "D": "They are capable of performing surgeries without human assistance"
        },
        "answer": "C"
    },
    {
        "question": "Which of the following statements best describes the role of AI in healthcare decision-making as per the given text?",
        "options": {
            "A": "AI should replace doctors entirely",
            "B": "AI enhances and complements doctors' roles",
            "C": "Doctors can rely solely on AI for decision-making",
            "D": "Doctors have no role in healthcare decisions with AI"
        },
        "answer": "B"
    },
    {
        "question": "Which of the following is a significant application of AI in healthcare?",
        "options": {
            "A": "Identifying common cold in X-rays and MRIs",
            "B": "Predicting weather patterns",
            "C": "Accurately identifying diseases such as cancer, pneumonia, and brain tumors in X-rays and MRIs",
            "D": "Analyzing financial market trends"
        },
        "answer": "C"
    }
]